tornado_openapi3/__init__.py
tornado_openapi3/handler.py
tornado_openapi3/py.typed
tornado_openapi3/requests.py
tornado_openapi3/responses.py
tornado_openapi3/testing.py
tornado_openapi3/types.py
tornado_openapi3/util.py
tornado_openapi3-1.2.0.dist-info/LICENSE
tornado_openapi3-1.2.0.dist-info/METADATA
tornado_openapi3-1.2.0.dist-info/WHEEL
tornado_openapi3-1.2.0.dist-info/RECORD
