Metadata-Version: 2.1
Name: tornado-openapi3
Version: 1.2.0
Summary: Tornado OpenAPI 3 request and response validation library
Home-page: https://github.com/correl/tornado-openapi3
License: MIT
Author: Correl Roush
Author-email: correl@gmail.com
Requires-Python: >=3.9,<4.0
Classifier: License :: OSI Approved :: MIT License
Classifier: Programming Language :: Python :: 3
Classifier: Programming Language :: Python :: 3.9
Classifier: Programming Language :: Python :: 3.10
Classifier: Programming Language :: Python :: 3.11
Classifier: Programming Language :: Python :: 3.12
Classifier: Programming Language :: Python :: 3.13
Requires-Dist: ietfparse (>=1.8.0,<2.0.0)
Requires-Dist: openapi-core (>=0.19.4,<0.20.0)
Requires-Dist: tornado (>=5,<7)
Requires-Dist: typing-extensions (>=4.0.1,<5.0.0)
Project-URL: Repository, https://github.com/correl/tornado-openapi3
